README.rst
setup.py
ripper/__init__.py
ripper/ripper.py
ripper/utils.py
ripper.egg-info/PKG-INFO
ripper.egg-info/SOURCES.txt
ripper.egg-info/dependency_links.txt
ripper.egg-info/not-zip-safe
ripper.egg-info/requires.txt
ripper.egg-info/top_level.txt