Metadata-Version: 1.0
Name: ripper
Version: 0.0.1
Summary: Image Ripper for the Pythonic Soul
Home-page: http://github.com/kevinaloys/ripper
Author: Kevin Aloysius
Author-email: kevinaloysius25@gmail.com
License: MIT
Platform: UNKNOWN
